HISTORY.rst
LICENSE
MANIFEST.in
README.rst
setup.py
mixcloud/__init__.py
mixcloud/mock.py
mixcloud.egg-info/PKG-INFO
mixcloud.egg-info/SOURCES.txt
mixcloud.egg-info/dependency_links.txt
mixcloud.egg-info/requires.txt
mixcloud.egg-info/top_level.txt