Metadata-Version: 1.1
Name: mixcloud
Version: 0.0.3
Summary: Bindings for the mixcloud.com API
Home-page: https://github.com/emillon/mixcloud
Author: Etienne Millon
Author-email: me@emillon.org
License: BSD
Platform: UNKNOWN
Classifier: Development Status :: 3 - Alpha
Classifier: Intended Audience :: Developers
Classifier: License :: OSI Approved :: BSD License
Classifier: Operating System :: OS Independent
Classifier: Programming Language :: Python :: 2
Classifier: Programming Language :: Python :: 3
